py3jsondb/__init__.py
py3jsondb/exceptions.py
py3jsondb/jsonpath.py
py3jsondb/search.py
py3jsondb/utils/__init__.py
py3jsondb/utils/combo_lock.py
py3jsondb-1.0.0.dist-info/LICENSE
py3jsondb-1.0.0.dist-info/METADATA
py3jsondb-1.0.0.dist-info/WHEEL
py3jsondb-1.0.0.dist-info/top_level.txt
py3jsondb-1.0.0.dist-info/RECORD
