Metadata-Version: 2.1
Name: py3jsondb
Version: 1.0.0
Summary: searchable json database, easy to add,update,delete and search in any level nested json tree
Home-page: https://github.com/alex-testlab/py3jsondb
Author: jarbasAI,Alex
Author-email: 
License: MIT
License-File: LICENSE
Requires-Dist: pyxdg
Requires-Dist: fasteners
